pangea_authn_fastmcp/__init__.py
pangea_authn_fastmcp/oauth_provider.py
pangea_authn_fastmcp/py.typed
pangea_authn_fastmcp/repositories/__init__.py
pangea_authn_fastmcp/repositories/in_memory_repository.py
pangea_authn_fastmcp/repositories/pangea_vault_repository.py
pangea_authn_fastmcp/repositories/repository.py
pangea_authn_fastmcp-0.3.1.dist-info/METADATA
pangea_authn_fastmcp-0.3.1.dist-info/WHEEL
pangea_authn_fastmcp-0.3.1.dist-info/licenses/LICENSE
pangea_authn_fastmcp-0.3.1.dist-info/RECORD
