Metadata-Version: 2.4
Name: pangea-authn-fastmcp
Version: 0.3.1
Summary: Pangea AuthN integration for FastMCP
Project-URL: Homepage, https://github.com/pangeacyber/pangea-authn-fastmcp
Project-URL: Documentation, https://github.com/pangeacyber/pangea-authn-fastmcp
Project-URL: Source, https://github.com/pangeacyber/pangea-authn-fastmcp
Project-URL: Changelog, https://github.com/pangeacyber/pangea-authn-fastmcp/releases
Author-email: Pangea <support@pangea.cloud>
License-Expression: MIT
License-File: LICENSE
Requires-Python: >=3.11
Requires-Dist: fastmcp>=2.11.3
Requires-Dist: httpx>=0.28.1
Requires-Dist: mcp>=1.13.0
Requires-Dist: pangea-sdk>=6.4.0
Requires-Dist: pydantic>=2.11.7
Requires-Dist: starlette>=0.47.2
